mypackage/__init__.py
mypackage/myanothermodule.py
mypackage/mymodule.py
pancopackage/__init__.py
pancopackage/myanothermodule.py
pancopackage/mymodule.py
pancopackage-1.2.dist-info/LICENSE
pancopackage-1.2.dist-info/METADATA
pancopackage-1.2.dist-info/WHEEL
pancopackage-1.2.dist-info/top_level.txt
pancopackage-1.2.dist-info/RECORD
